ZixueShiMenShouyi/README.md
ZixueShiMenShouyi/__init__.py
ZixueShiMenShouyi/__main__.py
ZixueShiMenShouyi/file.epub
ZixueShiMenShouyi/index.html
ZixueShiMenShouyi/css/__init__.py
ZixueShiMenShouyi/css/annotations.css
ZixueShiMenShouyi/css/main.css
ZixueShiMenShouyi/css/normalize.css
ZixueShiMenShouyi/css/popup.css
ZixueShiMenShouyi/font/__init__.py
ZixueShiMenShouyi/font/fontello.eot
ZixueShiMenShouyi/font/fontello.svg
ZixueShiMenShouyi/font/fontello.ttf
ZixueShiMenShouyi/font/fontello.woff
ZixueShiMenShouyi/img/__init__.py
ZixueShiMenShouyi/img/annotator-glyph-sprite.png
ZixueShiMenShouyi/img/annotator-icon-sprite.png
ZixueShiMenShouyi/img/apple-touch-icon.png
ZixueShiMenShouyi/img/cancelfullscreen.png
ZixueShiMenShouyi/img/close.png
ZixueShiMenShouyi/img/fullscreen.png
ZixueShiMenShouyi/img/loader.gif
ZixueShiMenShouyi/img/menu-icon.png
ZixueShiMenShouyi/img/save.png
ZixueShiMenShouyi/img/saved.png
ZixueShiMenShouyi/img/settings-s.png
ZixueShiMenShouyi/img/settings.png
ZixueShiMenShouyi/img/star.png
ZixueShiMenShouyi/js/__init__.py
ZixueShiMenShouyi/js/epub.js
ZixueShiMenShouyi/js/epub.min.js
ZixueShiMenShouyi/js/epub.min.map
ZixueShiMenShouyi/js/hooks.min.js
ZixueShiMenShouyi/js/hooks.min.map
ZixueShiMenShouyi/js/reader.js
ZixueShiMenShouyi/js/reader.js.map
ZixueShiMenShouyi/js/reader.min.js
ZixueShiMenShouyi/js/reader.min.map
ZixueShiMenShouyi/js/hooks/__init__.py
ZixueShiMenShouyi/js/hooks/extensions/__init__.py
ZixueShiMenShouyi/js/hooks/extensions/highlight.js
ZixueShiMenShouyi/js/libs/__init__.py
ZixueShiMenShouyi/js/libs/jquery.min.js
ZixueShiMenShouyi/js/libs/localforage.min.js
ZixueShiMenShouyi/js/libs/screenfull.js
ZixueShiMenShouyi/js/libs/screenfull.min.js
ZixueShiMenShouyi/js/libs/zip.min.js
ZixueShiMenShouyi/js/plugins/__init__.py
ZixueShiMenShouyi/js/plugins/hypothesis.js
ZixueShiMenShouyi/js/plugins/search.js
zixue_shi_men_shouyi-2024.3.5.0.dist-info/METADATA
zixue_shi_men_shouyi-2024.3.5.0.dist-info/WHEEL
zixue_shi_men_shouyi-2024.3.5.0.dist-info/entry_points.txt
zixue_shi_men_shouyi-2024.3.5.0.dist-info/top_level.txt
zixue_shi_men_shouyi-2024.3.5.0.dist-info/RECORD
